fake_plpy
