Metadata-Version: 1.1
Name: fake-plpy
Version: 0.0.2
Summary: Fake plpy
Home-page: https://github.com/viatoriche/fake_plpy
Author: viatoriche
Author-email: maxim@via-net.org
License: MIT
Download-URL: https://github.com/viatoriche/fake_plpy/tarball/0.0.2
Platform: UNKNOWN
